[1,0,0,[["cc.JsonAsset",["_name","json"],1]],[[0,0,1,3]],[[0,"113",{"version":1,"author":"","netName":"adv/113","config":{"distance":3500,"theme":"factory","date":1642645857939,"name":"工厂3"},"entity":[{"x":-300,"y":0,"i":"a","team":0,"me":1,"t":0,"c":1,"towers":[{"i":"b","m":1},{"i":"c","m":0},{"i":"d","m":0}],"heroes":[{"i":"h1"},{"i":"h2"},{"i":"h3"}],"bench":[{"i":"h4"}]},{"i":"bonus","ai":1,"t":0,"team":1,"flipX":1,"x":589.13,"y":375.65},{"i":"slime","ai":1,"t":0,"team":1,"flipX":1,"x":764.25,"y":203.13,"ground":"1"},{"i":"slime","ai":1,"t":0,"team":1,"flipX":1,"x":930.54,"y":200.63,"ground":"1"},{"i":"slime","ai":1,"t":0,"team":1,"flipX":1,"x":1013.04,"y":199.38,"ground":"1"},{"i":"slime","ai":1,"t":0,"team":1,"flipX":1,"x":749.25,"y":39.35},{"i":"slime","ai":1,"t":0,"team":1,"flipX":1,"x":924.29,"y":60.6},{"i":"slime","ai":1,"t":0,"team":1,"flipX":1,"x":1009.31,"y":36.84},{"i":"shenghuabing","ai":1,"t":0,"team":1,"flipX":1,"x":1281.53,"y":197.93,"ground":"1"},{"i":"shenghuabing","ai":1,"t":0,"team":1,"flipX":1,"x":1284.01,"y":30.33},{"i":"block2","ai":1,"t":0,"team":1,"flipX":1,"x":1120.43,"y":216.83,"ground":"1"},{"i":"block2","ai":1,"t":0,"team":1,"flipX":1,"x":1111.69,"y":59.34},{"i":"stage3","ai":1,"t":0,"team":1,"flipX":1,"x":1741.99,"y":249.4,"ground":"1"},{"i":"stage3","ai":1,"t":0,"team":1,"flipX":1,"x":2064.53,"y":249.34,"ground":"1"},{"i":"stage3","ai":1,"t":0,"team":1,"flipX":1,"x":1916.88,"y":394.22,"ground":"1"},{"i":"shenghuabing","ai":1,"t":0,"team":1,"flipX":1,"x":1911.98,"y":505.64,"ground":"1"},{"i":"shenghuabing","ai":1,"t":0,"team":1,"flipX":1,"x":2033.13,"y":414.36,"ground":"1"},{"i":"shenghuabing","ai":1,"t":0,"team":1,"flipX":1,"x":1904.53,"y":214.38,"ground":"1"},{"i":"slime","ai":1,"t":0,"team":1,"flipX":1,"x":1828.26,"y":504.46,"ground":"1"},{"i":"slime","ai":1,"t":0,"team":1,"flipX":1,"x":2154.59,"y":210.64,"ground":"1"},{"i":"slime","ai":1,"t":0,"team":1,"flipX":1,"x":2400.88,"y":206.85,"ground":"1"},{"i":"slime","ai":1,"t":0,"team":1,"flipX":1,"x":1670.65,"y":48.1},{"i":"slime","ai":1,"t":0,"team":1,"flipX":1,"x":2239.61,"y":26.84},{"i":"slime","ai":1,"t":0,"team":1,"flipX":1,"x":1506.93,"y":39.35},{"i":"slime","ai":1,"t":0,"team":1,"flipX":1,"x":1495.68,"y":206.89,"ground":"1"},{"i":"stage3","ai":1,"t":0,"team":1,"flipX":1,"x":3228.6,"y":248.15,"ground":"1"},{"i":"stage3","ai":1,"t":0,"team":1,"flipX":1,"x":3232.34,"y":403.08,"ground":"1"},{"i":"stage3","ai":1,"t":0,"team":1,"flipX":1,"x":3549.87,"y":245.65,"ground":"1"},{"i":"stage3","ai":1,"t":0,"team":1,"flipX":1,"x":3551.17,"y":401.93,"ground":"1"},{"i":"stage3","ai":1,"t":0,"team":1,"flipX":1,"x":3549.64,"y":554.32,"ground":"1"},{"i":"shenghuabing","ai":1,"t":0,"team":1,"flipX":1,"x":3504.85,"y":204.33,"ground":"1"},{"i":"shenghuabing","ai":1,"t":0,"team":1,"flipX":1,"x":3624.93,"y":501.9,"ground":"1"},{"i":"shenghuabing","ai":1,"t":0,"team":1,"flipX":1,"x":3429.9,"y":678.25,"ground":"1"},{"i":"rocketman","ai":1,"t":0,"team":1,"flipX":1,"x":3129.83,"y":503.21},{"i":"rocketman","ai":1,"t":0,"team":1,"flipX":1,"x":3429.9,"y":358.17},{"i":"rocketman","ai":1,"t":0,"team":1,"flipX":1,"x":3626.2,"y":35.59},{"i":"rocketman","ai":1,"t":0,"team":1,"flipX":1,"x":3638.7,"y":673.25},{"i":"slime","ai":1,"t":0,"team":1,"flipX":1,"x":3122.28,"y":201.88,"ground":"1"},{"i":"slime","ai":1,"t":0,"team":1,"flipX":1,"x":3671.21,"y":216.89,"ground":"1"},{"i":"slime","ai":1,"t":0,"team":1,"flipX":1,"x":3397.39,"y":499.46,"ground":"1"},{"i":"slime","ai":1,"t":0,"team":1,"flipX":1,"x":3568.68,"y":674.5,"ground":"1"},{"i":"e7","ai":1,"t":0,"team":1,"flipX":1,"x":3116.07,"y":351.92,"aiCfg":"{ctor:\"AICommon\",vx:-4,ax:1,at:3}","ground":"1"},{"i":"e7","ai":1,"t":0,"team":1,"flipX":1,"x":3172.34,"y":351.92,"aiCfg":"{ctor:\"AICommon\",vx:-4,ax:1,at:3}","ground":"1"},{"i":"e7","ai":1,"t":0,"team":1,"flipX":1,"x":3308.62,"y":343.17,"aiCfg":"{ctor:\"AICommon\",vx:-4,ax:1,at:3}","ground":"1"},{"i":"e7","ai":1,"t":0,"team":1,"flipX":1,"x":3341.13,"y":345.67,"aiCfg":"{ctor:\"AICommon\",vx:-4,ax:1,at:3}","ground":"1"},{"i":"e7","ai":1,"t":0,"team":1,"flipX":1,"x":3314.87,"y":199.38,"aiCfg":"{ctor:\"AICommon\",vx:-4,ax:1,at:3}","ground":"1"},{"i":"e7","ai":1,"t":0,"team":1,"flipX":1,"x":3407.39,"y":203.14,"aiCfg":"{ctor:\"AICommon\",vx:-4,ax:1,at:3}","ground":"1"},{"i":"e7","ai":1,"t":0,"team":1,"flipX":1,"x":3469.91,"y":205.64,"aiCfg":"{ctor:\"AICommon\",vx:-4,ax:1,at:3}","ground":"1"},{"i":"e7","ai":1,"t":0,"team":1,"flipX":1,"x":3571.18,"y":200.63,"aiCfg":"{ctor:\"AICommon\",vx:-4,ax:1,at:3}","ground":"1"},{"i":"e7","ai":1,"t":0,"team":1,"flipX":1,"x":3606.19,"y":194.38,"aiCfg":"{ctor:\"AICommon\",vx:-4,ax:1,at:3}","ground":"1"},{"i":"e7","ai":1,"t":0,"team":1,"flipX":1,"x":3494.92,"y":520.71,"aiCfg":"{ctor:\"AICommon\",vx:-4,ax:1,at:3}","ground":"1"},{"i":"e7","ai":1,"t":0,"team":1,"flipX":1,"x":3554.93,"y":506.96,"aiCfg":"{ctor:\"AICommon\",vx:-4,ax:1,at:3}","ground":"1"},{"i":"e7","ai":1,"t":0,"team":1,"flipX":1,"x":3631.2,"y":509.46,"aiCfg":"{ctor:\"AICommon\",vx:-4,ax:1,at:3}","ground":"1"},{"i":"e7","ai":1,"t":0,"team":1,"flipX":1,"x":3676.21,"y":508.21,"aiCfg":"{ctor:\"AICommon\",vx:-4,ax:1,at:3}","ground":"1"},{"i":"e7","ai":1,"t":0,"team":1,"flipX":1,"x":2703.4,"y":21.76,"aiCfg":"{ctor:\"AICommon\",vx:-4,ax:1,at:3}"},{"i":"e7","ai":1,"t":0,"team":1,"flipX":1,"x":2807.25,"y":26.84,"aiCfg":"{ctor:\"AICommon\",vx:-4,ax:1,at:3}"},{"i":"e7","ai":1,"t":0,"team":1,"flipX":1,"x":2994.79,"y":11.84,"aiCfg":"{ctor:\"AICommon\",vx:-4,ax:1,at:3}"},{"i":"e7","ai":1,"t":0,"team":1,"flipX":1,"x":3267.36,"y":19.34,"aiCfg":"{ctor:\"AICommon\",vx:-4,ax:1,at:3}"},{"i":"e7","ai":1,"t":0,"team":1,"flipX":1,"x":3413.65,"y":8.09,"aiCfg":"{ctor:\"AICommon\",vx:-4,ax:1,at:3}"},{"i":"e7","ai":1,"t":0,"team":1,"flipX":1,"x":3446.15,"y":61.85,"aiCfg":"{ctor:\"AICommon\",vx:-4,ax:1,at:3}"},{"i":"e7","ai":1,"t":0,"team":1,"flipX":1,"x":3653.7,"y":60.6,"aiCfg":"{ctor:\"AICommon\",vx:-4,ax:1,at:3}"},{"i":"e7","ai":1,"t":0,"team":1,"flipX":1,"x":3813.74,"y":51.85,"aiCfg":"{ctor:\"AICommon\",vx:-4,ax:1,at:3}"},{"i":"slime","ai":1,"t":0,"team":1,"flipX":1,"x":2699.72,"y":794.53,"ground":"1","xx":320},{"i":"slime","ai":1,"t":0,"team":1,"flipX":1,"x":2598.44,"y":798.28,"ground":"1","xx":435},{"i":"slime","ai":1,"t":0,"team":1,"flipX":1,"x":2490.88,"y":795.76,"ground":"1","xx":550},{"i":"slime","ai":1,"t":0,"team":1,"flipX":1,"x":2385.86,"y":798.28,"ground":"1","xx":665},{"i":"slime","ai":1,"t":0,"team":1,"flipX":1,"x":2284.59,"y":797.03,"ground":"1","xx":780},{"i":"e7","ai":1,"t":0,"team":1,"flipX":1,"x":2565.94,"y":49.35,"aiCfg":"{ctor:\"AICommon\",vx:-4,ax:1,at:3}"},{"i":"e7","ai":1,"t":0,"team":1,"flipX":1,"x":2457.16,"y":48.1,"aiCfg":"{ctor:\"AICommon\",vx:-4,ax:1,at:3}"},{"i":"e7","ai":1,"t":0,"team":1,"flipX":1,"x":2363.39,"y":21.84,"aiCfg":"{ctor:\"AICommon\",vx:-4,ax:1,at:3}"},{"i":"e7","ai":1,"t":0,"team":1,"flipX":1,"x":2562.19,"y":198.13,"aiCfg":"{ctor:\"AICommon\",vx:-4,ax:1,at:3}","ground":"1"},{"i":"e7","ai":1,"t":0,"team":1,"flipX":1,"x":2653.46,"y":204.39,"aiCfg":"{ctor:\"AICommon\",vx:-4,ax:1,at:3}","ground":"1"},{"i":"e7","ai":1,"t":0,"team":1,"flipX":1,"x":2603.4,"y":194.2,"aiCfg":"{ctor:\"AICommon\",vx:-4,ax:1,at:3}","ground":"1"},{"i":"e7","ai":1,"t":0,"team":1,"flipX":1,"x":2753.48,"y":196.88,"aiCfg":"{ctor:\"AICommon\",vx:-4,ax:1,at:3}","ground":"1"},{"i":"shenghuabing","ai":1,"t":0,"team":1,"flipX":1,"x":2885.86,"y":956.93,"g":"3","xx":444},{"i":"elevator","ai":1,"t":0,"team":1,"flipX":1,"x":1474.33,"y":512.58,"aiCfg":"{ctor:\"AIElevator\",moveX:0,moveY:-3,moveTime:2,delayTime:44}"},{"i":"shenghuabing","ai":1,"t":0,"team":1,"flipX":1,"x":1473.02,"y":525.07,"ground":"1"},{"i":"elevator","ai":1,"t":0,"team":1,"flipX":1,"x":3005.8,"y":941.91,"xx":444,"aiCfg":"{ctor:\"AIElevator\",moveX:0,moveY:-3,moveTime:2,delayTime:1}","g":"3"},{"i":"elevator","ai":1,"t":0,"team":1,"flipX":1,"x":2877.07,"y":941.98,"xx":444,"aiCfg":"{ctor:\"AIElevator\",moveX:0,moveY:-3,moveTime:2,delayTime:1}","g":"3"},{"i":"shenghuabing","ai":1,"t":0,"team":1,"flipX":1,"x":3008.34,"y":961.9,"g":"3","xx":444}],"ground":[{"i":0,"list":[]},{"i":1,"list":[{"x":855.5,"y":160.53}]}],"scene":[],"event":[]}]],0,0,[],[],[]]