[1,0,0,[["cc.JsonAsset",["_name","json"],1]],[[0,0,1,3]],[[0,"9",{"version":1,"author":"","netName":"adv/9","config":{"distance":3500,"theme":"snow","date":1649319382234},"entity":[{"x":-300,"y":0,"i":"a","team":0,"me":1,"t":0,"c":1,"towers":[{"i":"b","m":1},{"i":"c","m":0},{"i":"d","m":0}],"heroes":[{"i":"1"},{"i":"2"},{"i":"3"}],"bench":[{"i":"1"},{"i":"2"},{"i":"3"},{"i":"4"}]},{"i":"e6","ai":1,"t":0,"team":1,"flipX":1,"x":797.92,"y":448.4},{"i":"e6","ai":1,"t":0,"team":1,"flipX":1,"x":1050.05,"y":459.92},{"i":"e6","ai":1,"t":0,"team":1,"flipX":1,"x":894.86,"y":528.83},{"i":"e6","ai":1,"t":0,"team":1,"flipX":1,"x":858.87,"y":659.09},{"i":"e6","ai":1,"t":0,"team":1,"flipX":1,"x":993.58,"y":493.73},{"i":"e6","ai":1,"t":0,"team":1,"flipX":1,"x":916.66,"y":352.42},{"i":"e6","ai":1,"t":0,"team":1,"flipX":1,"x":981.7,"y":227.59},{"i":"e6","ai":1,"t":0,"team":1,"flipX":1,"x":804,"y":600.79},{"i":"e6","ai":1,"t":0,"team":1,"flipX":1,"x":988.26,"y":647.11},{"i":"e6","ai":1,"t":0,"team":1,"flipX":1,"x":1031.02,"y":330.5},{"i":"e6","ai":1,"t":0,"team":1,"flipX":1,"x":855.66,"y":348.6},{"i":"e6","ai":1,"t":0,"team":1,"flipX":1,"x":784.8,"y":324.7},{"i":"e6","ai":1,"t":0,"team":1,"flipX":1,"x":1281.01,"y":152.88},{"i":"e6","ai":1,"t":0,"team":1,"flipX":1,"x":1269.71,"y":363.73},{"i":"e6","ai":1,"t":0,"team":1,"flipX":1,"x":1585.98,"y":531.28},{"i":"e6","ai":1,"t":0,"team":1,"flipX":1,"x":1493.73,"y":256.43},{"i":"e6","ai":1,"t":0,"team":1,"flipX":1,"x":1378.9,"y":369.38},{"i":"e6","ai":1,"t":0,"team":1,"flipX":1,"x":1358.19,"y":567.04},{"i":"e6","ai":1,"t":0,"team":1,"flipX":1,"x":1574.68,"y":550.1},{"i":"e6","ai":1,"t":0,"team":1,"flipX":1,"x":1473.03,"y":439.04},{"i":"e6","ai":1,"t":0,"team":1,"flipX":1,"x":2585.6,"y":435.27},{"i":"e6","ai":1,"t":0,"team":1,"flipX":1,"x":2647.73,"y":454.1},{"i":"e6","ai":1,"t":0,"team":1,"flipX":1,"x":2519.71,"y":612.23},{"i":"e6","ai":1,"t":0,"team":1,"flipX":1,"x":2600.66,"y":572.69},{"i":"e6","ai":1,"t":0,"team":1,"flipX":1,"x":2877.39,"y":521.87},{"i":"e6","ai":1,"t":0,"team":1,"flipX":1,"x":2707.97,"y":367.5},{"i":"e6","ai":1,"t":0,"team":1,"flipX":1,"x":2585.6,"y":284.67},{"i":"e6","ai":1,"t":0,"team":1,"flipX":1,"x":2572.42,"y":250.78},{"i":"e6","ai":1,"t":0,"team":1,"flipX":1,"x":2553.6,"y":540.69},{"i":"e6","ai":1,"t":0,"team":1,"flipX":1,"x":2465.12,"y":303.49},{"i":"e6","ai":1,"t":0,"team":1,"flipX":1,"x":2858.57,"y":427.74},{"i":"e6","ai":1,"t":0,"team":1,"flipX":1,"x":2788.92,"y":585.87},{"i":"e6","ai":1,"t":0,"team":1,"flipX":1,"x":2675.96,"y":619.76},{"i":"e6","ai":1,"t":0,"team":1,"flipX":1,"x":2764.44,"y":390.09},{"i":"e6","ai":1,"t":0,"team":1,"flipX":1,"x":2828.45,"y":265.83},{"i":"e6","ai":1,"t":0,"team":1,"flipX":1,"x":2819.04,"y":256.43},{"i":"e6","ai":1,"t":0,"team":1,"flipX":1,"x":3607.82,"y":542.57},{"i":"e6","ai":1,"t":0,"team":1,"flipX":1,"x":3690.65,"y":542.57},{"i":"e6","ai":1,"t":0,"team":1,"flipX":1,"x":3502.39,"y":384.44},{"i":"e6","ai":1,"t":0,"team":1,"flipX":1,"x":3726.42,"y":371.26},{"i":"e6","ai":1,"t":0,"team":1,"flipX":1,"x":3628.52,"y":184.89},{"i":"e6","ai":1,"t":0,"team":1,"flipX":1,"x":3402.62,"y":309.14},{"i":"e6","ai":1,"t":0,"team":1,"flipX":1,"x":3773.48,"y":220.66},{"i":"e6","ai":1,"t":0,"team":1,"flipX":1,"x":3553.22,"y":354.32},{"i":"e6","ai":1,"t":0,"team":1,"flipX":1,"x":3583.34,"y":294.08},{"i":"e6","ai":1,"t":0,"team":1,"flipX":1,"x":3447.8,"y":583.99},{"i":"e6","ai":1,"t":0,"team":1,"flipX":1,"x":3445.92,"y":644.23},{"i":"e6","ai":1,"t":0,"team":1,"flipX":1,"x":3487.33,"y":523.75},{"i":"machinegun","ai":1,"t":0,"team":1,"flipX":1,"x":992.98,"y":105.83},{"i":"machinegun","ai":1,"t":0,"team":1,"flipX":1,"x":1670.69,"y":103.94},{"i":"machinegun","ai":1,"t":0,"team":1,"flipX":1,"x":2056.48,"y":284.58},{"i":"machinegun","ai":1,"t":0,"team":1,"flipX":1,"x":3137.18,"y":41.82},{"i":"machinegun","ai":1,"t":0,"team":1,"flipX":1,"x":3428.98,"y":38.06},{"i":"rocketman","ai":1,"t":0,"team":1,"flipX":1,"x":2948.93,"y":94.53},{"i":"rocketman","ai":1,"t":0,"team":1,"flipX":1,"x":2378.52,"y":230.07},{"i":"rocketman","ai":1,"t":0,"team":1,"flipX":1,"x":2495.23,"y":192.42},{"i":"rocketman","ai":1,"t":0,"team":1,"flipX":1,"x":1284.77,"y":87},{"i":"rocketman","ai":1,"t":0,"team":1,"flipX":1,"x":3726.42,"y":34.29},{"i":"e7","ai":1,"t":0,"team":1,"flipX":1,"x":2660.9,"y":162.3},{"i":"e7","ai":1,"t":0,"team":1,"flipX":1,"x":2721.14,"y":139.71},{"i":"e7","ai":1,"t":0,"team":1,"flipX":1,"x":2787.03,"y":124.65},{"i":"e7","ai":1,"t":0,"team":1,"flipX":1,"x":2845.39,"y":119.01},{"i":"e7","ai":1,"t":0,"team":1,"flipX":1,"x":2869.86,"y":94.53},{"i":"e7","ai":1,"t":0,"team":1,"flipX":1,"x":1947.42,"y":247.02},{"i":"e7","ai":1,"t":0,"team":1,"flipX":1,"x":1902.24,"y":211.25},{"i":"e7","ai":1,"t":0,"team":1,"flipX":1,"x":1855.18,"y":181.13},{"i":"e7","ai":1,"t":0,"team":1,"flipX":1,"x":1802.47,"y":151.01,"aiCfg":"{ctor:\"AICommon\",vx:-4,ax:1,at:3}"},{"i":"e7","ai":1,"t":0,"team":1,"flipX":1,"x":1450.44,"y":134.07,"aiCfg":"{ctor:\"AICommon\",vx:-4,ax:1,at:3}"},{"i":"e7","ai":1,"t":0,"team":1,"flipX":1,"x":1473.03,"y":124.65,"aiCfg":"{ctor:\"AICommon\",vx:-4,ax:1,at:3}"},{"i":"e7","ai":1,"t":0,"team":1,"flipX":1,"x":1457.97,"y":105.83,"aiCfg":"{ctor:\"AICommon\",vx:-4,ax:1,at:3}"},{"i":"e7","ai":1,"t":0,"team":1,"flipX":1,"x":1403.37,"y":103.94,"aiCfg":"{ctor:\"AICommon\",vx:-4,ax:1,at:3}"},{"i":"e7","ai":1,"t":0,"team":1,"flipX":1,"x":1540.8,"y":88.88,"aiCfg":"{ctor:\"AICommon\",vx:-4,ax:1,at:3}"},{"i":"e7","ai":1,"t":0,"team":1,"flipX":1,"x":864.97,"y":137.83,"aiCfg":"{ctor:\"AICommon\",vx:-4,ax:1,at:3}"},{"i":"e7","ai":1,"t":0,"team":1,"flipX":1,"x":684.25,"y":113.36,"aiCfg":"{ctor:\"AICommon\",vx:-3,ax:1,at:3}"},{"i":"e7","ai":1,"t":0,"team":1,"flipX":1,"x":592,"y":79.47,"aiCfg":"{ctor:\"AICommon\",vx:-3,ax:1,at:3}"},{"i":"e7","ai":1,"t":0,"team":1,"flipX":1,"x":541.16,"y":77.59,"aiCfg":"{ctor:\"AICommon\",vx:-3,ax:1,at:3}"},{"i":"e7","ai":1,"t":0,"team":1,"flipX":1,"x":1053.22,"y":154.77,"aiCfg":"{ctor:\"AICommon\",vx:-4,ax:1,at:3}"},{"i":"e7","ai":1,"t":0,"team":1,"flipX":1,"x":1200.06,"y":124.65,"aiCfg":"{ctor:\"AICommon\",vx:-4,ax:1,at:3}"},{"i":"e7","ai":1,"t":0,"team":1,"flipX":1,"x":1222.65,"y":105.83,"aiCfg":"{ctor:\"AICommon\",vx:-4,ax:1,at:3}"},{"i":"e7","ai":1,"t":0,"team":1,"flipX":1,"x":1083.33,"y":105.83,"aiCfg":"{ctor:\"AICommon\",vx:-4,ax:1,at:3}"},{"i":"e7","ai":1,"t":0,"team":1,"flipX":1,"x":1028.75,"y":120.89,"aiCfg":"{ctor:\"AICommon\",vx:-4,ax:1,at:3}"},{"i":"e7","ai":1,"t":0,"team":1,"flipX":1,"x":1194.41,"y":120.89,"aiCfg":"{ctor:\"AICommon\",vx:-4,ax:1,at:3}"},{"i":"e7","ai":1,"t":0,"team":1,"flipX":1,"x":1190.65,"y":143.47,"aiCfg":"{ctor:\"AICommon\",vx:-4,ax:1,at:3}"},{"i":"e7","ai":1,"t":0,"team":1,"flipX":1,"x":1143.58,"y":98.3,"aiCfg":"{ctor:\"AICommon\",vx:-4,ax:1,at:3}"},{"i":"e7","ai":1,"t":0,"team":1,"flipX":1,"x":2090.5,"y":275.26,"aiCfg":"{ctor:\"AICommon\",vx:-4,ax:1,at:3}"},{"i":"e7","ai":1,"t":0,"team":1,"flipX":1,"x":2084.85,"y":275.26,"aiCfg":"{ctor:\"AICommon\",vx:-4,ax:1,at:3}"},{"i":"e7","ai":1,"t":0,"team":1,"flipX":1,"x":2186.51,"y":252.66,"aiCfg":"{ctor:\"AICommon\",vx:-4,ax:1,at:3}"},{"i":"e7","ai":1,"t":0,"team":1,"flipX":1,"x":2288.16,"y":237.6,"aiCfg":"{ctor:\"AICommon\",vx:-4,ax:1,at:3}"},{"i":"e7","ai":1,"t":0,"team":1,"flipX":1,"x":2399.23,"y":226.31,"aiCfg":"{ctor:\"AICommon\",vx:-4,ax:1,at:3}"},{"i":"e7","ai":1,"t":0,"team":1,"flipX":1,"x":3193.66,"y":71.94,"aiCfg":"{ctor:\"AICommon\",vx:-4,ax:1,at:3}"},{"i":"e7","ai":1,"t":0,"team":1,"flipX":1,"x":3300.96,"y":71.94,"aiCfg":"{ctor:\"AICommon\",vx:-4,ax:1,at:3}"},{"i":"e7","ai":1,"t":0,"team":1,"flipX":1,"x":3449.68,"y":71.94,"aiCfg":"{ctor:\"AICommon\",vx:-4,ax:1,at:3}"},{"i":"e7","ai":1,"t":0,"team":1,"flipX":1,"x":3596.52,"y":70.06,"aiCfg":"{ctor:\"AICommon\",vx:-4,ax:1,at:3}"},{"i":"e7","ai":1,"t":0,"team":1,"flipX":1,"x":3745.24,"y":56.88,"aiCfg":"{ctor:\"AICommon\",vx:-4,ax:1,at:3}"},{"i":"e7","ai":1,"t":0,"team":1,"flipX":1,"x":3519.34,"y":34.29,"aiCfg":"{ctor:\"AICommon\",vx:-4,ax:1,at:3}"},{"i":"e7","ai":1,"t":0,"team":1,"flipX":1,"x":3270.84,"y":41.82,"aiCfg":"{ctor:\"AICommon\",vx:-4,ax:1,at:3}"},{"i":"e7","ai":1,"t":0,"team":1,"flipX":1,"x":3361.2,"y":30.53,"aiCfg":"{ctor:\"AICommon\",vx:-4,ax:1,at:3}"},{"i":"e7","ai":1,"t":0,"team":1,"flipX":1,"x":3622.88,"y":-22.18,"aiCfg":"{ctor:\"AICommon\",vx:-4,ax:1,at:3}"},{"i":"e7","ai":1,"t":0,"team":1,"flipX":1,"x":3818.66,"y":-22.18,"aiCfg":"{ctor:\"AICommon\",vx:-4,ax:1,at:3}"},{"i":"e7","ai":1,"t":0,"team":1,"flipX":1,"x":3963.61,"y":4.17,"aiCfg":"{ctor:\"AICommon\",vx:-4,ax:1,at:3}"},{"i":"e7","ai":1,"t":0,"team":1,"flipX":1,"x":3867.6,"y":98.3,"aiCfg":"{ctor:\"AICommon\",vx:-4,ax:1,at:3}"},{"i":"e7","ai":1,"t":0,"team":1,"flipX":1,"x":3888.31,"y":70.06,"aiCfg":"{ctor:\"AICommon\",vx:-4,ax:1,at:3}"},{"i":"e7","ai":1,"t":0,"team":1,"flipX":1,"x":3878.9,"y":4.17,"aiCfg":"{ctor:\"AICommon\",vx:-4,ax:1,at:3}"},{"i":"e7","ai":1,"t":0,"team":1,"flipX":1,"x":3807.36,"y":68.18,"aiCfg":"{ctor:\"AICommon\",vx:-4,ax:1,at:3}"},{"i":"helicopter","ai":1,"t":0,"team":1,"flipX":1,"x":2069.79,"y":563.28},{"i":"helicopter","ai":1,"t":0,"team":1,"flipX":1,"x":3203.03,"y":391.9},{"i":"helicopter","ai":1,"t":0,"team":1,"flipX":1,"x":1194.48,"y":499.6},{"i":"fort2","ai":1,"t":0,"team":1,"flipX":1,"x":1557.69,"y":143.46},{"i":"fort2","ai":1,"t":0,"team":1,"flipX":1,"x":878.12,"y":162.29},{"i":"fort2","ai":1,"t":0,"team":1,"flipX":1,"x":2088.6,"y":316.66},{"i":"fort2","ai":1,"t":0,"team":1,"flipX":1,"x":2092.35,"y":461.6},{"i":"fort2","ai":1,"t":0,"team":1,"flipX":1,"x":3647.35,"y":85.12},{"i":"fort2","ai":1,"t":0,"team":1,"flipX":1,"x":3647.35,"y":222.54},{"i":"fort2","ai":1,"t":0,"team":1,"flipX":1,"x":3643.58,"y":350.56},{"i":"rocketman","ai":1,"t":0,"team":1,"flipX":1,"x":3613.46,"y":71.94},{"i":"rocketman","ai":1,"t":0,"team":1,"flipX":1,"x":3611.58,"y":230.07},{"i":"rocketman","ai":1,"t":0,"team":1,"flipX":1,"x":3604.05,"y":390.09}],"ground":[{"i":0,"list":[{"x":177.85,"y":0},{"x":725.64,"y":107.27},{"x":1264.03,"y":90.33},{"x":1623.63,"y":68.18},{"x":1802.37,"y":133.56},{"x":1986.94,"y":239.46},{"x":2229.75,"y":239.42},{"x":2538.48,"y":146.73},{"x":2751.22,"y":101.61},{"x":3457.21,"y":0},{"x":3690.65,"y":0},{"x":3886.43,"y":0}]}],"scene":[],"event":[]}]],0,0,[],[],[]]